inspector_commons/__init__.py
inspector_commons/api/__init__.py
inspector_commons/api/bridge_interface.py
inspector_commons/api/database_interface.py
inspector_commons/bridge/__init__.py
inspector_commons/bridge/base.py
inspector_commons/bridge/bridge_browser.py
inspector_commons/bridge/bridge_recorder.py
inspector_commons/bridge/bridge_windows.py
inspector_commons/bridge/mixin.py
inspector_commons/config.py
inspector_commons/context.py
inspector_commons/database.py
inspector_commons/driver_web.py
inspector_commons/driver_windows.py
inspector_commons/metric.py
inspector_commons/static/resources/browser-recording-guide.html
inspector_commons/static/resources/builder.js
inspector_commons/static/resources/builder.js.LICENSE.txt
inspector_commons/static/resources/guide.html
inspector_commons/static/resources/inspector.css
inspector_commons/static/resources/inspector.js
inspector_commons/static/resources/inspector.js.LICENSE.txt
inspector_commons/static/resources/webRecorder.js
inspector_commons/static/resources/webRecorder.js.LICENSE.txt
inspector_commons/telemetry.py
inspector_commons/utils.py
robocorp_inspector_commons-0.10.2.dist-info/LICENSE
robocorp_inspector_commons-0.10.2.dist-info/METADATA
robocorp_inspector_commons-0.10.2.dist-info/WHEEL
robocorp_inspector_commons-0.10.2.dist-info/RECORD
