Metadata-Version: 2.1
Name: robocorp-inspector-commons
Version: 0.10.2
Summary: Robocorp Inspector Commons
Home-page: https://github.com/robocorp/inspector
License: Proprietary
Author: Robocorp
Author-email: dev@robocorp.com
Requires-Python: >=3.8,<3.11
Classifier: License :: Other/Proprietary License
Classifier: Programming Language :: Python :: 3
Classifier: Programming Language :: Python :: 3.8
Classifier: Programming Language :: Python :: 3.9
Classifier: Programming Language :: Python :: 3.10
Requires-Dist: psutil (==5.9.4)
Requires-Dist: pynput-robocorp-fork (==5.0.0) ; sys_platform == "win32"
Requires-Dist: pywin32 (>=302,<304) ; python_full_version != "3.7.6" and python_full_version != "3.8.1" and sys_platform == "win32"
Requires-Dist: requests (==2.28.1)
Requires-Dist: retry (==0.9.2)
Requires-Dist: rpaframework-core (==11.0.6)
Requires-Dist: types-retry (==0.9.9.2)
Requires-Dist: typing-extensions (==4.4.0)
Requires-Dist: uiautomation (==2.0.16) ; sys_platform == "win32"
Project-URL: Repository, https://github.com/robocorp/inspector
